bannerify/__init__.py
bannerify/client.py
bannerify/models.py
bannerify/py.typed
bannerify-0.3.0.dist-info/WHEEL
bannerify-0.3.0.dist-info/METADATA
bannerify-0.3.0.dist-info/RECORD
