Metadata-Version: 2.3
Name: bannerify
Version: 0.3.0
Summary: Official Python SDK for Bannerify API - Generate images and PDFs at scale
Keywords: bannerify,image generation,pdf generation,api
Author: Duc An
Author-email: Duc An <an@bannerify.co>
License: MIT
Classifier: Development Status :: 4 - Beta
Classifier: Intended Audience :: Developers
Classifier: License :: OSI Approved :: MIT License
Classifier: Programming Language :: Python :: 3
Classifier: Programming Language :: Python :: 3.8
Classifier: Programming Language :: Python :: 3.9
Classifier: Programming Language :: Python :: 3.10
Classifier: Programming Language :: Python :: 3.11
Classifier: Programming Language :: Python :: 3.12
Requires-Dist: httpx>=0.27.0
Requires-Dist: pydantic>=2.0
Requires-Dist: python-dotenv>=1.0.1
Requires-Python: >=3.8
Project-URL: Documentation, https://bannerify.co/docs
Project-URL: Homepage, https://bannerify.co
Project-URL: Issues, https://github.com/bannerify/bannerify-python/issues
Project-URL: Repository, https://github.com/bannerify/bannerify-python
